{"board_size": 8, "board": "###r#r#s\n#sledo#k\n#p#g#w#a\n#rmatcht\n#i#t#f#e\n#nstroke\n#t#a#u##\n#javelin", "number_of_intersections": 6, "words_with_descriptions": {"regatta": "A series of boat races.", "skate": "The action of moving or gliding over a surface, especially ice or a smooth floor, using skates.", "sprint": "A short, fast race run at full speed over a limited distance.", "javelin": "A sport in which a spear is thrown as far as possible.", "match": "A sports contest or game where individuals or teams compete against each other.", "sled": "The act or sport of riding on a sled or using it, especially in snowy conditions.", "foul": "An unfair or illegal sports action that breaks the rules of the game.", "stroke": "A single complete movement, often used in swimming and rowing.", "row": "The act of propelling a boat using oars."}, "words_coordinates": {"regatta": [0, 3, "vertical"], "skate": [0, 7, "vertical"], "sprint": [1, 1, "vertical"], "javelin": [7, 1, "horizontal"], "match": [3, 2, "horizontal"], "sled": [1, 1, "horizontal"], "foul": [4, 5, "vertical"], "stroke": [5, 2, "horizontal"], "row": [0, 5, "vertical"]}}