{"board_size": 8, "board": "###p###t\nsuburb#a\n#f#b###x\n#ashop#i\n#c###a##\ngalleria\n#d###k##\nterminal", "number_of_intersections": 5, "words_with_descriptions": {"facade": "The face of a building, especially the principal front that looks onto a street or open space.", "pub": "A local bar or tavern where people gather to drink and socialize.", "taxi": "A car available for hire with a driver, used for transporting passengers.", "terminal": "A departure and arrival building for passengers at an airport, seaport, or bus station.", "galleria": "An often large and luxurious indoor facility featuring a collection of shops, restaurants, and sometimes entertainment outlets.", "park": "A public area with open space for recreation and relaxation.", "shop": "A small retail establishment selling items to the public.", "suburb": "An outlying district of a city, especially a residential one."}, "words_coordinates": {"facade": [2, 1, "vertical"], "pub": [0, 3, "vertical"], "taxi": [0, 7, "vertical"], "terminal": [7, 0, "horizontal"], "galleria": [5, 0, "horizontal"], "park": [3, 5, "vertical"], "shop": [3, 2, "horizontal"], "suburb": [1, 0, "horizontal"]}}